sqlservice/__init__.py
sqlservice/async_database.py
sqlservice/async_session.py
sqlservice/database.py
sqlservice/database_abc.py
sqlservice/database_settings.py
sqlservice/event.py
sqlservice/model.py
sqlservice/session.py
sqlservice/utils.py
sqlservice-3.0.0.dist-info/AUTHORS.rst
sqlservice-3.0.0.dist-info/LICENSE.rst
sqlservice-3.0.0.dist-info/METADATA
sqlservice-3.0.0.dist-info/WHEEL
sqlservice-3.0.0.dist-info/top_level.txt
sqlservice-3.0.0.dist-info/RECORD
