Metadata-Version: 2.1
Name: sqlservice
Version: 3.0.0
Summary: The missing SQLAlchemy ORM interface
Home-page: https://github.com/dgilland/sqlservice
Author: Derrick Gilland
Author-email: dgilland@gmail.com
License: MIT License
Keywords: sqlservice sqlalchemy orm database
Classifier: Development Status :: 5 - Production/Stable
Classifier: License :: OSI Approved :: MIT License
Classifier: Intended Audience :: Developers
Classifier: Operating System :: OS Independent
Classifier: Programming Language :: Python
Classifier: Programming Language :: Python :: 3
Classifier: Programming Language :: Python :: 3.7
Classifier: Programming Language :: Python :: 3.8
Classifier: Programming Language :: Python :: 3.9
Classifier: Programming Language :: Python :: 3.10
Classifier: Programming Language :: Python :: 3.11
Classifier: Topic :: Database
Classifier: Topic :: Database :: Front-Ends
Classifier: Topic :: Software Development :: Libraries
Classifier: Topic :: Software Development :: Libraries :: Python Modules
Requires-Python: >=3.7
License-File: LICENSE.rst
License-File: AUTHORS.rst
Requires-Dist: SQLAlchemy >=2.0
Provides-Extra: dev
Requires-Dist: aiosqlite ; extra == 'dev'
Requires-Dist: black ; extra == 'dev'
Requires-Dist: build ; extra == 'dev'
Requires-Dist: coverage ; extra == 'dev'
Requires-Dist: docformatter ; extra == 'dev'
Requires-Dist: flake8 ; extra == 'dev'
Requires-Dist: flake8-black ; extra == 'dev'
Requires-Dist: flake8-bugbear ; extra == 'dev'
Requires-Dist: flake8-isort ; extra == 'dev'
Requires-Dist: furo ; extra == 'dev'
Requires-Dist: greenlet ; extra == 'dev'
Requires-Dist: invoke ; extra == 'dev'
Requires-Dist: isort ; extra == 'dev'
Requires-Dist: mock ; extra == 'dev'
Requires-Dist: mypy ; extra == 'dev'
Requires-Dist: pylint ; extra == 'dev'
Requires-Dist: pytest ; extra == 'dev'
Requires-Dist: pytest-asyncio ; extra == 'dev'
Requires-Dist: pytest-cov ; extra == 'dev'
Requires-Dist: sphinx ; extra == 'dev'
Requires-Dist: sphinx-autodoc-typehints ; extra == 'dev'
Requires-Dist: tox ; extra == 'dev'
Requires-Dist: types-mock ; extra == 'dev'
Requires-Dist: twine ; extra == 'dev'
Requires-Dist: wheel ; extra == 'dev'
Requires-Dist: importlib-metadata <5 ; (python_version == "3.7") and extra == 'dev'
